langchain_superlinked-0.1.1.dist-info/METADATA
langchain_superlinked-0.1.1.dist-info/WHEEL
langchain_superlinked-0.1.1.dist-info/entry_points.txt
langchain_superlinked-0.1.1.dist-info/licenses/LICENSE
langchain_superlinked/__init__.py
langchain_superlinked/py.typed
langchain_superlinked/retrievers.py
langchain_superlinked-0.1.1.dist-info/RECORD
