Metadata-Version: 2.1
Name: langchain-superlinked
Version: 0.1.1
Summary: An integration package connecting Superlinked and LangChain
License: MIT
Project-URL: Homepage, https://github.com/superlinked/langchain-superlinked
Project-URL: Repository, https://github.com/superlinked/langchain-superlinked
Project-URL: Source Code, https://github.com/superlinked/langchain-superlinked
Project-URL: Release Notes, https://github.com/superlinked/langchain-superlinked/releases
Project-URL: Bug Tracker, https://github.com/superlinked/langchain-superlinked/issues
Requires-Python: <3.14,>=3.10
Requires-Dist: langchain-core<1.0.0,>=0.3.15
Requires-Dist: superlinked==33.5.1
Requires-Dist: pandas<3.0.0,>=2.2.0
